test_test000000000000/__init__.py
test_test000000000000-0.0.1.dist-info/METADATA
test_test000000000000-0.0.1.dist-info/WHEEL
test_test000000000000-0.0.1.dist-info/top_level.txt
test_test000000000000-0.0.1.dist-info/RECORD
